{
    "chunk1":  "      await dbHelper.runQuery(\u0027UPDATE announcements SET is_pinned = FALSE WHERE id = $1\u0027, [annId]);\n      await this.apiCall(\u0027answerCallbackQuery\u0027, { callback_query_id: callbackQuery.id, text: \u0027?? ????? Ø§Ù„ØªØ«Ø¨ÙŠØª Ù„Ø¯Ù‰ Ø§Ù„Ø¬Ù…ÙŠØ¹.\u0027, show_alert: true });\n      await this.apiCall(\u0027deleteMessage\u0027, { chat_id: chatId, message_id: callbackQuery.message.message_id }).catch(() =\u003e {});",
    "chunk6":  "        if (text !== \u0027/skip\u0027 \u0026\u0026 text !== \u0027/skip (ØªØ®Ø·ÙŠ Ø¨Ø¯ÙˆÙ† Ù…Ù„Ù)\u0027 \u0026\u0026 text !== t(lang, \u0027MSG_ADMIN_35\u0027)) {\n          doc = this.extractTelegramAttachment(message);",
    "chunk5":  "            [{ text: t(lang, \u0027BTN_BACK\u0027) }]\n          ];",
    "chunk3":  "          const cfgText = (lang === \u0027ar\u0027 ? \u0027Ø¥Ø¹Ø¯Ø§Ø¯Ø§Øª\\n\\nØ§Ù„Ù…Ø±Ø§Ù‚Ø¨Ø©: \u0027 : \u0027Settings\\n\\nMonitoring: \u0027) + monStatus;\n          const cfgKb = [",
    "chunk4":  "            [{ text: t(lang, \u0027BTN_BACK\u0027) }]\n          ];",
    "chunk8":  "               const txt = `ðŸ“¢ *${msgTitle}*\\n\\n${msgContent}\\n\\n${updatedAnn.is_pinned ? \u0027ðŸ“Œ (Pinned)\u0027 : \u0027\u0027}`;\n               await this.apiCall(\u0027editMessageText\u0027, { chat_id: msg.chat_id, message_id: msg.message_id, text: txt, parse_mode: \u0027Markdown\u0027 });",
    "chunk2":  "        const statsAr = `ðŸ“Š **Ø¥Ø­ØµØ§Ø¦ÙŠØ§Øª Ø§Ù„Ø¨ÙˆØª Ø§Ù„Ø´Ø§Ù…Ù„Ø©:**\\n\\n` +\n          `ðŸ‘¥ **Ø§Ù„Ù…Ø´ØªØ±ÙƒÙˆÙ†**\\n` +\n          `- Ø¥Ø¬Ù…Ø§Ù„ÙŠ Ø§Ù„Ù…Ø´ØªØ±ÙƒÙŠÙ†: ${totalUsers}\\n` +\n          `- Ø§Ù„Ù…Ø´ØªØ±ÙƒÙˆÙ† Ø§Ù„Ø¬Ø¯Ø¯ (Ø£Ø³Ø¨ÙˆØ¹): ${weeklySubscribers}\\n` +\n          `- Ø§Ù„Ù…Ø´ØªØ±ÙƒÙˆÙ† Ø§Ù„Ø¬Ø¯Ø¯ (Ø´Ù‡Ø±): ${monthlySubscribers}\\n\\n` +\n          `ðŸ“ˆ **Ø§Ù„Ù†Ø´Ø§Ø·**\\n` +\n          `- Ù†Ø´Ø· Ø§Ù„ÙŠÙˆÙ…: ${dailyActive}\\n` +\n          `- Ù†Ø´Ø· Ù‡Ø°Ø§ Ø§Ù„Ø£Ø³Ø¨ÙˆØ¹: ${weeklyActive}\\n` +\n          `- Ù†Ø´Ø· Ù‡Ø°Ø§ Ø§Ù„Ø´Ù‡Ø±: ${monthlyActive}\\n\\n` +\n          `ðŸš€ **Ø§Ù„Ø£Ø¯Ø§Ø¡ ÙˆØ§Ù„ØªÙØ§Ø¹Ù„**\\n` +\n          `- Ù†Ø³Ø¨Ø© Ø§Ù„ÙˆØµÙˆÙ„ (Ø´Ù‡Ø±ÙŠØ§Ù‹): ${reachPercentage}%\\n` +\n          `- Ø¥Ø¬Ù…Ø§Ù„ÙŠ Ø§Ù„Ø·Ù„Ø¨Ø§Øª/Ø§Ù„ØªÙØ§Ø¹Ù„Ø§Øª: ${totalRequests}\\n` +\n          `- Ø²Ù…Ù† Ø§Ù„Ø§Ø³ØªØ¬Ø§Ø¨Ø© (Ù…ØªÙˆØ³Ø·): ${avgLatency}ms\\n\\n` +\n          `ðŸ—‚ï¸ **Ø§Ù„Ù…Ø­ØªÙˆÙ‰**\\n` +\n          `- Ø¹Ø¯Ø¯ Ø§Ù„Ø£Ø²Ø±Ø§Ø± Ø§Ù„Ù…ØªØ§Ø­Ø©: ${totalButtons}\\n` +\n          `- Ø¹Ø¯Ø¯ Ø§Ù„Ù…Ù„ÙØ§Øª Ø§Ù„Ù…Ø±ÙÙˆØ¹Ø©: ${totalFiles}\\n` +\n          `- Ø§Ù„Ø²Ø± Ø§Ù„Ø£ÙƒØ«Ø± Ø·Ù„Ø¨Ø§Ù‹: ${topButtonStr}\\n\\n` +\n          `ðŸ›‘ **Ø§Ù„Ø­Ø¸Ø±**\\n` +\n          `- Ø¹Ø¯Ø¯ Ù…Ù† Ù‚Ø§Ù… Ø¨Ø­Ø¸Ø± Ø£Ùˆ Ø­Ø°Ù Ø§Ù„Ø¨ÙˆØª: ${blockedUsers}`;\n          ",
    "chunk7":  "        state.isPinned = text === \u0027Ù†Ø¹Ù… (ØªØ«Ø¨ÙŠØª)\u0027 || text === \u0027Yes (Pin)\u0027 || text === t(lang, \u0027MSG_ADMIN_38\u0027);\n        await this.handleAdminAnnouncementBroadcast(chatId, state, lang);"
}
